<annotation>
	<folder>mixed</folder>
	<filename>typewritten_image_41.png</filename>
	<path>C:\Users\d.shukiraliyev\Desktop\Table_detection\data\mixed\typewritten_image_41.png</path>
	<source>
		<database>Unknown</database>
	</source>
	<size>
		<width>523</width>
		<height>739</height>
		<depth>3</depth>
	</size>
	<segmented>0</segmented>
	<object>
		<name>Borderless</name>
		<pose>Unspecified</pose>
		<truncated>1</truncated>
		<difficult>0</difficult>
		<bndbox>
			<xmin>2</xmin>
			<ymin>537</ymin>
			<xmax>523</xmax>
			<ymax>738</ymax>
		</bndbox>
	</object>
</annotation>
